rt_pie/__init__.py
rt_pie/arg_parser.py
rt_pie/config.py
rt_pie/file_processor.py
rt_pie/fitted_models.py
rt_pie/microphone_processor.py
rt_pie/performance_analyzer.py
rt_pie/plotter.py
rt_pie/rt_pie_lib/__init__.py
rt_pie/rt_pie_lib/config/__init__.py
rt_pie/rt_pie_lib/converters/__init__.py
rt_pie/rt_pie_lib/metrics/__init__.py
rt_pie/rt_pie_lib/metrics/unvoiced_detector/__init__.py
rt_pie/rt_pie_lib/networks/__init__.py
rt_pie/rt_pie_lib/networks/checkpoint_to_model_converter.py
rt_pie/rt_pie_lib/networks/crepe.py
rt_pie/rt_pie_lib/networks/deepf0.py
rt_pie/rt_pie_lib/networks/lstm.py
rt_pie/serialized_models/deepf0_1024_512_e087_model.hdf5
rt_pie/serialized_models/deepf0_1024_512_reduced_filter_e100_model.hdf5
rt_pie/serialized_models/deepf0_2048_1024_e100_model.hdf5
rt_pie/serialized_models/deepf0_512_256_e048_model.hdf5
rt_pie/serialized_models/lstm_1024_512_e100_model.hdf5
rt_pie/serialized_models/lstm_256_128_e092_model.hdf5
rt_pie/serialized_models/lstm_512_256_e065_model.hdf5
rt_pie/stream_processor.py
rt_pie-0.1.15.dist-info/entry_points.txt
rt_pie-0.1.15.dist-info/WHEEL
rt_pie-0.1.15.dist-info/METADATA
rt_pie-0.1.15.dist-info/RECORD
